dojogen-1.1.0.dist-info/DESCRIPTION.rst
dojogen-1.1.0.dist-info/WHEEL
dojogen-1.1.0.dist-info/RECORD
dojogen-1.1.0.dist-info/entry_points.txt
dojogen-1.1.0.dist-info/METADATA
dojogen-1.1.0.dist-info/metadata.json
dojogen-1.1.0.dist-info/top_level.txt
dojogen/__init__.py
dojogen/dojogen.py
dojogen/generators/renomear.sh
dojogen/generators/renomear.sh~
dojogen/generators/moonscript/.dojoignore
dojogen/generators/moonscript/___dojogen____spec.moon
dojogen/generators/moonscript/run.dojo
dojogen/generators/moonscript/___dojogen___.moon
dojogen/generators/javascript/___class_dojogen___Spec.js
dojogen/generators/javascript/run.dojo
dojogen/generators/javascript/___class_dojogen___.js
dojogen/generators/pascal/Test___class_dojogen___.pas
dojogen/generators/pascal/.dojoignore
dojogen/generators/pascal/TestUnit.pas
dojogen/generators/pascal/___class_dojogen___Unit.pas
dojogen/generators/pascal/run.dojo
dojogen/generators/python/.dojoignore
dojogen/generators/python/test____dojogen___.py
dojogen/generators/python/___dojogen___.py
dojogen/generators/python/run.dojo
dojogen/generators/java/build.xml
dojogen/generators/java/junit.jar
dojogen/generators/java/.dojoignore
dojogen/generators/java/manifest.mf
dojogen/generators/java/run.dojo
dojogen/generators/java/src/___down_dojogen___/___class_dojogen___.java
dojogen/generators/java/test/Test___class_dojogen___.java
dojogen/generators/java/lib/junit.jar
dojogen/generators/java/build/test/classes/.netbeans_automatic_build
dojogen/generators/java/build/classes/.netbeans_automatic_build
dojogen/generators/java/nbproject/build-impl.xml
dojogen/generators/java/nbproject/project.properties
dojogen/generators/java/nbproject/project.xml
dojogen/generators/java/nbproject/genfiles.properties
dojogen/generators/java/nbproject/private/private.properties
dojogen/generators/coffeescript/___dojogen___.spec.coffee
dojogen/generators/coffeescript/.dojoignore
dojogen/generators/coffeescript/run.dojo
dojogen/generators/coffeescript/___dojogen___.coffee
dojogen/generators/c/.dojoignore
dojogen/generators/c/test___down_dojogen___.c
dojogen/generators/c/run.dojo
dojogen/generators/c/___down_dojogen___.c
dojogen/generators/c/simplectest/tests.h
