Metadata-Version: 1.0
Name: dojogen
Version: 1.1.0
Summary: Generates folders for coding dojo sessions
Home-page: https://github.com/dojorio/dojogen
Author: ('Joao Pimentel',)
Author-email: joaofelipenp@gmail.com
License: MIT
Keywords: dojo generate languages
Platform: UNKNOWN
